ibm_quantum_schemas/__init__.py
ibm_quantum_schemas/_version.py
ibm_quantum_schemas/aliases.py
ibm_quantum_schemas/models/__init__.py
ibm_quantum_schemas/models/annotation_serializer.py
ibm_quantum_schemas/models/base_params_model.py
ibm_quantum_schemas/models/pauli_lindblad_map_model.py
ibm_quantum_schemas/models/qpy_model.py
ibm_quantum_schemas/models/samplex_model.py
ibm_quantum_schemas/models/tensor_model.py
ibm_quantum_schemas/models/executor/__init__.py
ibm_quantum_schemas/models/executor/version_0_1/__init__.py
ibm_quantum_schemas/models/executor/version_0_1/models.py
ibm_quantum_schemas/models/executor/version_0_1/validate.py
ibm_quantum_schemas/models/executor/version_0_2_dev/__init__.py
ibm_quantum_schemas/models/executor/version_0_2_dev/models.py
ibm_quantum_schemas/models/noise_learner_v3/__init__.py
ibm_quantum_schemas/models/noise_learner_v3/version_0_1/__init__.py
ibm_quantum_schemas/models/noise_learner_v3/version_0_1/models.py
ibm_quantum_schemas/models/noise_learner_v3/version_0_1/validate.py
ibm_quantum_schemas/models/noise_learner_v3/version_0_2_dev/__init__.py
ibm_quantum_schemas/models/noise_learner_v3/version_0_2_dev/models.py
ibm_quantum_schemas-0.1.20260129.dist-info/licenses/LICENSE.txt
ibm_quantum_schemas-0.1.20260129.dist-info/METADATA
ibm_quantum_schemas-0.1.20260129.dist-info/WHEEL
ibm_quantum_schemas-0.1.20260129.dist-info/top_level.txt
ibm_quantum_schemas-0.1.20260129.dist-info/RECORD
