Metadata-Version: 2.4
Name: ibm-quantum-schemas
Version: 0.1.20260129
Summary: IBM Quantum Pydantic models.
Author-email: Qiskit Development Team <qiskit@us.ibm.com>
License-Expression: Apache-2.0
Project-URL: Homepage, https://github.com/Qiskit/ibm-quantum-schemas
Project-URL: BugTracker, https://github.com/Qiskit/ibm-quantum-schemas
Classifier: Development Status :: 3 - Alpha
Classifier: Intended Audience :: Developers
Classifier: Programming Language :: Python
Classifier: Programming Language :: Python :: 3
Classifier: Programming Language :: Python :: 3.11
Requires-Python: >=3.10
License-File: LICENSE.txt
Requires-Dist: pydantic<3.0.0,>=2.5
Requires-Dist: qiskit<3.0.0,>=2.2.0
Requires-Dist: samplomatic>=0.12.0
Provides-Extra: dev
Requires-Dist: pre-commit; extra == "dev"
Requires-Dist: pytest; extra == "dev"
Requires-Dist: pytest-error-for-skips; extra == "dev"
Requires-Dist: ruff; extra == "dev"
Requires-Dist: towncrier; extra == "dev"
Dynamic: license-file
